LICENSE
MANIFEST.in
README.md
VERSION
pyproject.toml
qgis_plugin_manager/__about__.py
qgis_plugin_manager/__init__.py
qgis_plugin_manager/__main__.py
qgis_plugin_manager/definitions.py
qgis_plugin_manager/echo.py
qgis_plugin_manager/local_directory.py
qgis_plugin_manager/remote.py
qgis_plugin_manager/utils.py
qgis_plugin_manager.egg-info/PKG-INFO
qgis_plugin_manager.egg-info/SOURCES.txt
qgis_plugin_manager.egg-info/dependency_links.txt
qgis_plugin_manager.egg-info/entry_points.txt
qgis_plugin_manager.egg-info/requires.txt
qgis_plugin_manager.egg-info/top_level.txt