Metadata-Version: 2.4
Name: qgis-plugin-manager
Version: 1.7.5
Summary: Tool for downloading/managing QGIS plugins from CLI.
Author: Étienne Trimaille
Maintainer-email: David Marteau <dmarteau@3liz.com>
License-Expression: GPL-3.0-or-later
Keywords: QGIS
Classifier: Development Status :: 5 - Production/Stable
Classifier: Intended Audience :: System Administrators
Classifier: Intended Audience :: Developers
Classifier: Intended Audience :: Information Technology
Classifier: Operating System :: OS Independent
Classifier: Programming Language :: Python :: 3
Classifier: Programming Language :: Python :: 3.9
Classifier: Programming Language :: Python :: 3.10
Classifier: Programming Language :: Python :: 3.11
Classifier: Programming Language :: Python :: 3.12
Classifier: Programming Language :: Python :: 3.13
Classifier: Programming Language :: Python :: Implementation :: CPython
Classifier: Topic :: Scientific/Engineering :: GIS
Requires-Python: >=3.9
License-File: LICENSE
Requires-Dist: semver==3.0.4
Dynamic: license-file
